oblib/__init__.py
oblib/constants.py
oblib/data_model.py
oblib/identifier.py
oblib/ob.py
oblib/parser.py
oblib/taxonomy.py
oblib/taxonomy_loader.py
oblib/util.py
oblib/validator.py
oblib/data/solar-taxonomy/.gitignore
oblib/data/solar-taxonomy/LICENSE
oblib/data/solar-taxonomy/README.md
oblib/data/solar-taxonomy/.git/HEAD
oblib/data/solar-taxonomy/.git/config
oblib/data/solar-taxonomy/.git/description
oblib/data/solar-taxonomy/.git/index
oblib/data/solar-taxonomy/.git/packed-refs
oblib/data/solar-taxonomy/.git/hooks/applypatch-msg.sample
oblib/data/solar-taxonomy/.git/hooks/commit-msg.sample
oblib/data/solar-taxonomy/.git/hooks/fsmonitor-watchman.sample
oblib/data/solar-taxonomy/.git/hooks/post-update.sample
oblib/data/solar-taxonomy/.git/hooks/pre-applypatch.sample
oblib/data/solar-taxonomy/.git/hooks/pre-commit.sample
oblib/data/solar-taxonomy/.git/hooks/pre-push.sample
oblib/data/solar-taxonomy/.git/hooks/pre-rebase.sample
oblib/data/solar-taxonomy/.git/hooks/pre-receive.sample
oblib/data/solar-taxonomy/.git/hooks/prepare-commit-msg.sample
oblib/data/solar-taxonomy/.git/hooks/update.sample
oblib/data/solar-taxonomy/.git/info/exclude
oblib/data/solar-taxonomy/.git/logs/HEAD
oblib/data/solar-taxonomy/.git/logs/refs/remotes/origin/HEAD
oblib/data/solar-taxonomy/.git/objects/pack/pack-2e45d480f09f782e769e9b0abdc3da02afd9b0c8.idx
oblib/data/solar-taxonomy/.git/objects/pack/pack-2e45d480f09f782e769e9b0abdc3da02afd9b0c8.pack
oblib/data/solar-taxonomy/.git/refs/remotes/origin/HEAD
oblib/data/solar-taxonomy/META-INF/taxonomyPackage.xml
oblib/data/solar-taxonomy/core/numeric-us-2017-03-31.xsd
oblib/data/solar-taxonomy/core/solar-gen-roles-2018-03-31.xsd
oblib/data/solar-taxonomy/core/solar-ref-parts_2018-03-31.xsd
oblib/data/solar-taxonomy/core/solar-ref-roles_2018-03-31.xsd
oblib/data/solar-taxonomy/core/solar-types-2020-04-01.xsd
oblib/data/solar-taxonomy/core/solar_2020-04-01.xsd
oblib/data/solar-taxonomy/core/solar_2020-04-01_lab.xml
oblib-1.1.3.dist-info/LICENSE
oblib-1.1.3.dist-info/METADATA
oblib-1.1.3.dist-info/WHEEL
oblib-1.1.3.dist-info/top_level.txt
oblib-1.1.3.dist-info/RECORD
